pdmongo/__init__.py
pdmongo/core.py
pdmongo-0.3.4.dist-info/AUTHORS.rst
pdmongo-0.3.4.dist-info/LICENSE
pdmongo-0.3.4.dist-info/METADATA
pdmongo-0.3.4.dist-info/WHEEL
pdmongo-0.3.4.dist-info/top_level.txt
pdmongo-0.3.4.dist-info/RECORD
