Metadata-Version: 2.1
Name: pdmongo
Version: 0.3.4
Summary: Transfer data between pandas dataframes and MongoDB
Home-page: https://github.com/pakallis/python-pandas-mongo
Author: Pavlos Kallis
Author-email: pakallis@gmail.com
License: MIT
Project-URL: Documentation, https://python-pandas-mongo.readthedocs.io/
Project-URL: Changelog, https://python-pandas-mongo.readthedocs.io/en/latest/changelog.html
Project-URL: Issue Tracker, https://github.com/pakallis/python-pandas-mongo/issues
Classifier: Development Status :: 5 - Production/Stable
Classifier: Intended Audience :: Developers
Classifier: License :: OSI Approved :: MIT License
Classifier: Operating System :: Unix
Classifier: Operating System :: POSIX
Classifier: Operating System :: Microsoft :: Windows
Classifier: Programming Language :: Python
Classifier: Programming Language :: Python :: 3
Classifier: Programming Language :: Python :: 3.7
Classifier: Programming Language :: Python :: 3.8
Classifier: Programming Language :: Python :: 3.9
Classifier: Programming Language :: Python :: 3.10
Classifier: Programming Language :: Python :: Implementation :: CPython
Classifier: Topic :: Utilities
Requires-Python: >=3.7
License-File: LICENSE
License-File: AUTHORS.rst
Requires-Dist: pymongo (<4.4,>=3.13)
Requires-Dist: pandas (<1.6,>=0.20)
Provides-Extra: test
Requires-Dist: pytest (>=4.0.2) ; extra == 'test'
Requires-Dist: pytest-mock (>=1.10.0) ; extra == 'test'
